git2version/__init__.py
git2version/make_git_version.py
git2version-0.1.67.dist-info/LICENSE
git2version-0.1.67.dist-info/METADATA
git2version-0.1.67.dist-info/WHEEL
git2version-0.1.67.dist-info/top_level.txt
git2version-0.1.67.dist-info/RECORD
